codereviewbot/__init__.py
codereviewbot/author.py
codereviewbot/codereviewbot.py
codereviewbot/constants.py
codereviewbot/gitOperations.py
codereviewbot/main.py
codereviewbot/read_config.py
codereviewbot/reviewCode.py
codereviewbot/reviewer.py
codereviewbot/utilities.py
codereviewbot-0.9.dist-info/LICENSE.txt
codereviewbot-0.9.dist-info/METADATA
codereviewbot-0.9.dist-info/WHEEL
codereviewbot-0.9.dist-info/top_level.txt
codereviewbot-0.9.dist-info/RECORD
