Metadata-Version: 2.1
Name: codereviewbot
Version: 0.9
Summary: This is a code review bot. Where you can review your code or other's code and get the feedback.
Author: Sriram
Author-email: Sriram.Chembrolu@powerschool.com
Classifier: Programming Language :: Python :: 3
Classifier: License :: OSI Approved :: MIT License
Classifier: Operating System :: OS Independent
Requires-Python: >=3.8
License-File: LICENSE.txt
Requires-Dist: rich
